{
  "id": "advert",
  "type": "SharedSlice",
  "name": "Advert",
  "description": "Advert",
  "variations": [
    {
      "id": "default",
      "name": "Default",
      "docURL": "...",
      "version": "initial",
      "description": "Default",
      "imageUrl": "",
      "primary": {
        "title": {
          "type": "Text",
          "config": { "label": "title", "placeholder": "" }
        },
        "text": {
          "type": "StructuredText",
          "config": {
            "label": "text",
            "placeholder": "",
            "allowTargetBlank": true,
            "multi": "paragraph,em,embed,list-item,strong"
          }
        },
        "buttonLink": {
          "type": "Link",
          "config": {
            "label": "Button link",
            "placeholder": "",
            "allowTargetBlank": true,
            "select": null
          }
        },
        "buttonLabel": {
          "type": "Text",
          "config": { "label": "Button label", "placeholder": "" }
        }
      },
      "items": {}
    }
  ]
}
